torchpress/__init__.py
torchpress/ndct.py
torchpress-0.0.1.dist-info/METADATA
torchpress-0.0.1.dist-info/WHEEL
torchpress-0.0.1.dist-info/licenses/LICENSE
torchpress-0.0.1.dist-info/RECORD
