Metadata-Version: 2.4
Name: torchpress
Version: 0.0.1
Summary: A compressor for nd-tensor with discrete cosine transform
Project-URL: Homepage, https://github.com/LHan7/NDCT
Project-URL: Issues, https://github.com/LHan7/NDCT/issues
Author-email: LHan <1155217600@link.cuhk.edu.hk>
License: MIT License
License-File: LICENSE
Classifier: Operating System :: OS Independent
Classifier: Programming Language :: Python :: 3
Requires-Python: >=3.9
Requires-Dist: einops
Requires-Dist: scipy
Requires-Dist: torch
Requires-Dist: torch-dct
